moroccan_prayer_times/__init__.py
moroccan_prayer_times/main.py
moroccan_prayer_times/translations/ar.yml
moroccan_prayer_times/translations/en.yml
moroccan_prayer_times/translations/fr.yml
moroccan_prayer_times-1.2.0.dist-info/LICENSE
moroccan_prayer_times-1.2.0.dist-info/METADATA
moroccan_prayer_times-1.2.0.dist-info/WHEEL
moroccan_prayer_times-1.2.0.dist-info/entry_points.txt
moroccan_prayer_times-1.2.0.dist-info/top_level.txt
moroccan_prayer_times-1.2.0.dist-info/RECORD
