Metadata-Version: 2.1
Name: moroccan-prayer-times
Version: 1.2.0
Summary: Moroccan Prayer Times CLI
Home-page: https://github.com/ismailbenhallam/moroccan-prayer-times/
Author: Ismail BENHALLAM
Author-email: ismailben44@gmail.com
Keywords: prayer times,prayer_times,prayer,morocco
Classifier: Environment :: Console
Classifier: Programming Language :: Python :: 3.11
Classifier: License :: OSI Approved :: MIT License
Classifier: Operating System :: OS Independent
Requires-Python: >=3.11
License-File: LICENSE
Requires-Dist: beautifulsoup4==4.12.3
Requires-Dist: beautifultable==1.1.0
Requires-Dist: click==8.1.7
Requires-Dist: InquirerPy==0.3.4
Requires-Dist: packaging==24.0
Requires-Dist: pyi18n-v2==1.2.1
Requires-Dist: Requests==2.32.3
Requires-Dist: rich==13.7.1
Requires-Dist: typer==0.12.3
Requires-Dist: urllib3==2.2.1
